sqlean/__init__.pyi
sqlean/dbapi2.pyi
sqlean/extensions.pyi
sqlean/py.typed
sqlean_stubs-0.0.8.dist-info/licenses/LICENSE
sqlean_stubs-0.0.8.dist-info/METADATA
sqlean_stubs-0.0.8.dist-info/WHEEL
sqlean_stubs-0.0.8.dist-info/top_level.txt
sqlean_stubs-0.0.8.dist-info/RECORD
