Metadata-Version: 2.4
Name: sqlean-stubs
Version: 0.0.8
Summary: Type hints for sqlean.py (sqlite3 + extensions)
Author-email: Kracekumar <me@kracekumar.com>
License: Zlib
Project-URL: Repository, https://github.com/kracekumar/sqlean-stubs
Project-URL: Documentation, https://github.com/kracekumar/sqlean-stubs
Project-URL: Bug Tracker, https://github.com/kracekumar/sqlean-stubs/issues
Keywords: sqlite,sqlean,type-hints,stubs,type-checking
Classifier: Development Status :: 5 - Production/Stable
Classifier: Intended Audience :: Developers
Classifier: License :: OSI Approved :: zlib/libpng License
Classifier: Programming Language :: Python :: 3
Classifier: Programming Language :: Python :: 3.9
Classifier: Programming Language :: Python :: 3.10
Classifier: Programming Language :: Python :: 3.11
Classifier: Programming Language :: Python :: 3.12
Classifier: Programming Language :: Python :: 3.13
Classifier: Programming Language :: Python :: 3.14
Classifier: Typing :: Typed
Requires-Python: >=3.9
License-File: LICENSE
Provides-Extra: dev
Requires-Dist: pytest>=7.0; extra == "dev"
Requires-Dist: mypy>=1.0; extra == "dev"
Requires-Dist: ty>=0.0.7; extra == "dev"
Requires-Dist: ruff>=0.1.0; extra == "dev"
Requires-Dist: tox>=4.0; extra == "dev"
Requires-Dist: sqlean.py>=3.50; extra == "dev"
Dynamic: license-file
